grstools/__init__.py
grstools/utils.py
grstools/version.py
grstools/scripts/__init__.py
grstools/scripts/build_grs.py
grstools/scripts/choose_snps.py
grstools/scripts/evaluate.py
grstools/scripts/mendelian_randomization.py
grstools/scripts/utils/__init__.py
grstools/scripts/utils/annotate_nearest_gene.py
grstools/scripts/utils/beta_plot.py
grstools/scripts/utils/core.py
grstools/scripts/utils/correlation.py
grstools/scripts/utils/histogram.py
grstools/scripts/utils/locus_overlap.py
grstools/scripts/utils/quantiles.py
grstools/scripts/utils/standardize.py
grstools/tests/__init__.py
grstools/tests/test_beta_plot.py
grstools/tests/test_grs_compute.py
grstools/tests/test_snp_selection.py
grstools/tests/test_utils.py
grstools-0.4.0.dist-info/DESCRIPTION.rst
grstools-0.4.0.dist-info/METADATA
grstools-0.4.0.dist-info/RECORD
grstools-0.4.0.dist-info/WHEEL
grstools-0.4.0.dist-info/entry_points.txt
grstools-0.4.0.dist-info/metadata.json
grstools-0.4.0.dist-info/top_level.txt
