Metadata-Version: 2.0
Name: grstools
Version: 0.4.0
Summary: Tools to manipulate genetic risk scores.
Home-page: https://github.com/legaultmarc/grstools
Author: Marc-André Legault
Author-email: legaultmarc@gmail.com
License: MIT
Keywords: bioinformatics genomics grs genetic risk score
Platform: UNKNOWN
Classifier: Development Status :: 4 - Beta
Classifier: Intended Audience :: Developers
Classifier: Intended Audience :: Science/Research
Classifier: Operating System :: Unix
Classifier: Operating System :: MacOS :: MacOS X
Classifier: Operating System :: POSIX :: Linux
Classifier: Programming Language :: Python
Classifier: Programming Language :: Python :: 3
Classifier: Topic :: Scientific/Engineering :: Bio-Informatics
Requires-Dist: geneparse (>=0.1.0)
Requires-Dist: genetest (>=0.1.0)
Requires-Dist: matplotlib (>=2.0)
Requires-Dist: scipy (>=0.18)
